leek/__init__.py
leek/base_queue.py
leek/custom_gevent.py
leek/custom_thread.py
leek/default_config.py
leek/init_config_file.py
leek/kafka_queue.py
leek/memery_queue.py
leek/middleware_eum.py
leek/redis_queue.py
leek/sqllite_queue.py
leek/task_consumer.py
leek/task_publisher.py
leek/test_demo.py
leek/utils.py
leek-1.7.3.dist-info/licenses/LICENSE.rst
leek-1.7.3.dist-info/METADATA
leek-1.7.3.dist-info/WHEEL
leek-1.7.3.dist-info/top_level.txt
leek-1.7.3.dist-info/RECORD
