Metadata-Version: 2.4
Name: leek
Version: 1.7.3
Summary: Task publishing and consumption Middleware
Home-page: https://github.com/abo123456789/redisqueue/tree/leek
Author: cc
Author-email: abcdef123456chen@sohu.com
Maintainer: cc
Maintainer-email: abcdef123456chen@sohu.com
License: MIT License
Keywords: redisqueue,queue-tasks,redis,distributed-scraper,producer-consumer,distribute-crawler,leek
Platform: all
Classifier: Development Status :: 4 - Beta
Classifier: Operating System :: OS Independent
Classifier: Intended Audience :: Developers
Classifier: License :: OSI Approved :: MIT License
Classifier: Programming Language :: Python
Classifier: Programming Language :: Python :: Implementation
Classifier: Programming Language :: Python :: 3.6
Classifier: Programming Language :: Python :: 3.7
Classifier: Programming Language :: Python :: 3.8
Classifier: Programming Language :: Python :: 3.9
Classifier: Programming Language :: Python :: 3.10
Classifier: Topic :: Software Development :: Libraries
License-File: LICENSE.rst
Requires-Dist: redis>=2.10.6
Requires-Dist: tomorrow3>=1.1.0
Requires-Dist: retrying>=1.3.3
Requires-Dist: loguru>=0.7.3
Requires-Dist: persist-queue>=0.5.0
Requires-Dist: gevent>=1.5.0
Requires-Dist: kafka-python
Requires-Dist: pypattyrn
Dynamic: author
Dynamic: author-email
Dynamic: classifier
Dynamic: description
Dynamic: description-content-type
Dynamic: home-page
Dynamic: keywords
Dynamic: license
Dynamic: license-file
Dynamic: maintainer
Dynamic: maintainer-email
Dynamic: platform
Dynamic: requires-dist
Dynamic: summary
